src/__init__.py
src/gitlabci_lint/__init__.py
src/gitlabci_lint/cli.py
pre_commit_gitlabci_lint-1.4.0.dist-info/LICENSE
pre_commit_gitlabci_lint-1.4.0.dist-info/METADATA
pre_commit_gitlabci_lint-1.4.0.dist-info/WHEEL
pre_commit_gitlabci_lint-1.4.0.dist-info/entry_points.txt
pre_commit_gitlabci_lint-1.4.0.dist-info/RECORD
