Metadata-Version: 2.1
Name: pre-commit-gitlabci-lint
Version: 1.4.0
Summary: Validate GitLab CI templates with a GitLab instance's API endpoint
License: MIT
Author: Emma Doyle
Author-email: emma.ann.doyle@gmail.com
Requires-Python: >=3.8,<4.0
Classifier: License :: OSI Approved :: MIT License
Classifier: Programming Language :: Python :: 3
Classifier: Programming Language :: Python :: 3.8
Classifier: Programming Language :: Python :: 3.9
Classifier: Programming Language :: Python :: 3.10
Classifier: Programming Language :: Python :: 3.11
Requires-Dist: toml (>=0.10.2,<0.11.0)
